gym_gwen/__init__.py
gym_gwen/envs/__init__.py
gym_gwen/envs/gwen_env.py
gym_gwen-0.0.1.dist-info/METADATA
gym_gwen-0.0.1.dist-info/WHEEL
gym_gwen-0.0.1.dist-info/top_level.txt
gym_gwen-0.0.1.dist-info/RECORD
