Metadata-Version: 2.1
Name: gym-gwen
Version: 0.0.1
Summary: A OpenAI Gym Env for gwen
Home-page: UNKNOWN
License: UNKNOWN
Platform: UNKNOWN
Requires-Dist: gym
Requires-Dist: pybullet
